{"cid":252,"name":"dihydrobiopterin","properties":{"CID":252,"MolecularFormula":"C9H13N5O3","MolecularWeight":239.23122,"IUPACName":"2-amino-6-(1,2-dihydroxypropyl)-7,8-dihydro-1H-pteridin-4-one","common_name":"dihydrobiopterin","common_names":["dihydrobiopterin","7,8-dihydrobiopterin","7,8-Dihydro-L-biopterin","L-erythro-q-dihydrobiopterin","2-amino-6-(1,2-dihydroxypropyl)-7,8-dihydro-4(1h)-pteridinon"]},"description":{"CID":252,"Title":"7,8-dihydrobiopterin","Description":"7,8-dihydrobiopterin is an inhibitor of the enzyme dihydroneopterin aldolase (DHNA), which catalyzes the conversion of 7,8-dihydroneopterin to 6-hydroxymethyl-7,8-dihydropterin and glycolaldehyde.","DescriptionSourceName":"DrugBank","DescriptionURL":"http://drugbank.ca/drugs/DB04400"},"structure":{"atoms":{"1":{"aid":1,"element":"o","x":2.9562,"y":0.2193,"z":1.7786},"2":{"aid":2,"element":"o","x":3.0955,"y":0.0222,"z":-1.8613},"3":{"aid":3,"element":"o","x":-1.1898,"y":2.5464,"z":0.2318},"4":{"aid":4,"element":"n","x":-0.5609,"y":-2.1118,"z":0.0241},"5":{"aid":5,"element":"n","x":0.5375,"y":0.4294,"z":0.3003},"6":{"aid":6,"element":"n","x":-2.7407,"y":-1.0865,"z":-0.1574},"7":{"aid":7,"element":"n","x":-3.0592,"y":1.2465,"z":-0.0535},"8":{"aid":8,"element":"n","x":-4.8667,"y":-0.2306,"z":-0.3442},"9":{"aid":9,"element":"c","x":2.8021,"y":-0.3749,"z":0.5021},"10":{"aid":10,"element":"c","x":1.323,"y":-0.6059,"z":0.3223},"11":{"aid":11,"element":"c","x":0.8688,"y":-2.0456,"z":0.178},"12":{"aid":12,"element":"c","x":3.374,"y":0.551,"z":-0.5654},"13":{"aid":13,"element":"c","x":-1.3768,"y":-1.0045,"z":-0.0005},"14":{"aid":14,"element":"c","x":-0.8094,"y":0.2128,"z":0.1357},"15":{"aid":15,"element":"c","x":4.8752,"y":0.764,"z":-0.4216},"16":{"aid":16,"element":"c","x":-1.6966,"y":1.4334,"z":0.1098},"17":{"aid":17,"element":"c","x":-3.5322,"y":0.0348,"z":-0.1788},"18":{"aid":18,"element":"h","x":3.3188,"y":-1.3405,"z":0.4981},"19":{"aid":19,"element":"h","x":1.3605,"y":-2.4834,"z":-0.6964},"20":{"aid":20,"element":"h","x":1.1756,"y":-2.6024,"z":1.069},"21":{"aid":21,"element":"h","x":2.8897,"y":1.5338,"z":-0.5073},"22":{"aid":22,"element":"h","x":-1.0088,"y":-3.0156,"z":-0.0802},"23":{"aid":23,"element":"h","x":5.1294,"y":1.2108,"z":0.5441},"24":{"aid":24,"element":"h","x":5.2476,"y":1.4211,"z":-1.2149},"25":{"aid":25,"element":"h","x":5.4135,"y":-0.1849,"z":-0.5224},"26":{"aid":26,"element":"h","x":-3.1353,"y":-2.015,"z":-0.2574},"27":{"aid":27,"element":"h","x":2.5634,"y":1.1086,"z":1.7515},"28":{"aid":28,"element":"h","x":3.4471,"y":0.6488,"z":-2.5165},"29":{"aid":29,"element":"h","x":-5.2096,"y":-1.1803,"z":-0.4391},"30":{"aid":30,"element":"h","x":-5.5506,"y":0.5175,"z":-0.3759}},"bonds":{"1":{"bid":1,"vertices":[1,9],"order":"single"},"2":{"bid":2,"vertices":[1,27],"order":"single"},"3":{"bid":3,"vertices":[2,12],"order":"single"},"4":{"bid":4,"vertices":[2,28],"order":"single"},"5":{"bid":5,"vertices":[3,16],"order":"double"},"6":{"bid":6,"vertices":[4,11],"order":"single"},"7":{"bid":7,"vertices":[4,13],"order":"single"},"8":{"bid":8,"vertices":[4,22],"order":"single"},"9":{"bid":9,"vertices":[5,10],"order":"double"},"10":{"bid":10,"vertices":[5,14],"order":"single"},"11":{"bid":11,"vertices":[6,13],"order":"single"},"12":{"bid":12,"vertices":[6,17],"order":"single"},"13":{"bid":13,"vertices":[6,26],"order":"single"},"14":{"bid":14,"vertices":[7,16],"order":"single"},"15":{"bid":15,"vertices":[7,17],"order":"double"},"16":{"bid":16,"vertices":[8,17],"order":"single"},"17":{"bid":17,"vertices":[8,29],"order":"single"},"18":{"bid":18,"vertices":[8,30],"order":"single"},"19":{"bid":19,"vertices":[9,10],"order":"single"},"20":{"bid":20,"vertices":[9,12],"order":"single"},"21":{"bid":21,"vertices":[9,18],"order":"single"},"22":{"bid":22,"vertices":[10,11],"order":"single"},"23":{"bid":23,"vertices":[11,19],"order":"single"},"24":{"bid":24,"vertices":[11,20],"order":"single"},"25":{"bid":25,"vertices":[12,15],"order":"single"},"26":{"bid":26,"vertices":[12,21],"order":"single"},"27":{"bid":27,"vertices":[13,14],"order":"double"},"28":{"bid":28,"vertices":[14,16],"order":"single"},"29":{"bid":29,"vertices":[15,23],"order":"single"},"30":{"bid":30,"vertices":[15,24],"order":"single"},"31":{"bid":31,"vertices":[15,25],"order":"single"}}}}