{"cid":310,"name":"2,4-Hexadienedioic acid","properties":{"CID":310,"MolecularFormula":"C6H6O4","MolecularWeight":142.10944,"IUPACName":"hexa-2,4-dienedioic acid","common_name":"2,4-Hexadienedioic acid","common_names":["2,4-Hexadienedioic acid","3588-17-8","CIS CIS-MUCONIC ACID","1119-72-8","505-70-4"]},"description":{"CID":310,"Title":"2,4-Hexadienedioic acid"},"structure":{"atoms":{"1":{"aid":1,"element":"o","x":-4.0227,"y":-0.922,"z":-0.001},"2":{"aid":2,"element":"o","x":4.0231,"y":0.9215,"z":-0.0006},"3":{"aid":3,"element":"o","x":-3.3636,"y":1.2621,"z":0.0008},"4":{"aid":4,"element":"o","x":3.363,"y":-1.2625,"z":0.0009},"5":{"aid":5,"element":"c","x":-0.6752,"y":0.2605,"z":-0.0002},"6":{"aid":6,"element":"c","x":0.6752,"y":-0.2599,"z":-0.0001},"7":{"aid":7,"element":"c","x":-1.756,"y":-0.5313,"z":0.0001},"8":{"aid":8,"element":"c","x":1.7562,"y":0.5317,"z":-0.0005},"9":{"aid":9,"element":"c","x":-3.1032,"y":0.071,"z":0.0004},"10":{"aid":10,"element":"c","x":3.1031,"y":-0.0711,"z":0.0001},"11":{"aid":11,"element":"h","x":-0.7841,"y":1.3423,"z":-0.0003},"12":{"aid":12,"element":"h","x":0.784,"y":-1.3417,"z":0.0004},"13":{"aid":13,"element":"h","x":-1.6747,"y":-1.6135,"z":0.0002},"14":{"aid":14,"element":"h","x":1.6752,"y":1.6139,"z":-0.0009},"15":{"aid":15,"element":"h","x":-4.9398,"y":-0.5736,"z":-0.0012},"16":{"aid":16,"element":"h","x":4.94,"y":0.5728,"z":-0.0003}},"bonds":{"1":{"bid":1,"vertices":[1,9],"order":"single"},"2":{"bid":2,"vertices":[1,15],"order":"single"},"3":{"bid":3,"vertices":[2,10],"order":"single"},"4":{"bid":4,"vertices":[2,16],"order":"single"},"5":{"bid":5,"vertices":[3,9],"order":"double"},"6":{"bid":6,"vertices":[4,10],"order":"double"},"7":{"bid":7,"vertices":[5,6],"order":"single"},"8":{"bid":8,"vertices":[5,7],"order":"double"},"9":{"bid":9,"vertices":[5,11],"order":"single"},"10":{"bid":10,"vertices":[6,8],"order":"double"},"11":{"bid":11,"vertices":[6,12],"order":"single"},"12":{"bid":12,"vertices":[7,9],"order":"single"},"13":{"bid":13,"vertices":[7,13],"order":"single"},"14":{"bid":14,"vertices":[8,10],"order":"single"},"15":{"bid":15,"vertices":[8,14],"order":"single"}}}}