{"cid":335,"name":"o-cresol","properties":{"CID":335,"MolecularFormula":"C7H8O","MolecularWeight":108.13782,"IUPACName":"2-methylphenol","common_name":"o-cresol","common_names":["o-cresol","2-Methylphenol","2-hydroxytoluene","o-methylphenol","2-Cresol"]},"description":{"CID":335,"Title":"2-cresol"},"structure":{"atoms":{"1":{"aid":1,"element":"o","x":1.6857,"y":-1.5029,"z":0},"2":{"aid":2,"element":"c","x":0.6382,"y":0.6532,"z":-0.0001},"3":{"aid":3,"element":"c","x":0.5573,"y":-0.7393,"z":0},"4":{"aid":4,"element":"c","x":-0.5273,"y":1.4196,"z":0},"5":{"aid":5,"element":"c","x":1.9637,"y":1.3405,"z":0.0001},"6":{"aid":6,"element":"c","x":-0.6891,"y":-1.3654,"z":0.0001},"7":{"aid":7,"element":"c","x":-1.7737,"y":0.7934,"z":0},"8":{"aid":8,"element":"c","x":-1.8547,"y":-0.5991,"z":0},"9":{"aid":9,"element":"h","x":-0.4819,"y":2.5054,"z":0.0001},"10":{"aid":10,"element":"h","x":2.5347,"y":1.0651,"z":0.8929},"11":{"aid":11,"element":"h","x":2.5356,"y":1.0638,"z":-0.8918},"12":{"aid":12,"element":"h","x":1.8594,"y":2.4308,"z":-0.0008},"13":{"aid":13,"element":"h","x":-0.7672,"y":-2.4493,"z":0.0001},"14":{"aid":14,"element":"h","x":-2.6813,"y":1.3899,"z":0},"15":{"aid":15,"element":"h","x":-2.8253,"y":-1.0865,"z":0},"16":{"aid":16,"element":"h","x":1.4333,"y":-2.4422,"z":0}},"bonds":{"1":{"bid":1,"vertices":[1,3],"order":"single"},"2":{"bid":2,"vertices":[1,16],"order":"single"},"3":{"bid":3,"vertices":[2,3],"order":"single"},"4":{"bid":4,"vertices":[2,4],"order":"double"},"5":{"bid":5,"vertices":[2,5],"order":"single"},"6":{"bid":6,"vertices":[3,6],"order":"double"},"7":{"bid":7,"vertices":[4,7],"order":"single"},"8":{"bid":8,"vertices":[4,9],"order":"single"},"9":{"bid":9,"vertices":[5,10],"order":"single"},"10":{"bid":10,"vertices":[5,11],"order":"single"},"11":{"bid":11,"vertices":[5,12],"order":"single"},"12":{"bid":12,"vertices":[6,8],"order":"single"},"13":{"bid":13,"vertices":[6,13],"order":"single"},"14":{"bid":14,"vertices":[7,8],"order":"double"},"15":{"bid":15,"vertices":[7,14],"order":"single"},"16":{"bid":16,"vertices":[8,15],"order":"single"}}}}