{"cid":484,"name":"4-aminoimidazole","properties":{"CID":484,"MolecularFormula":"C3H5N3","MolecularWeight":83.0919,"IUPACName":"1H-imidazol-5-amine","common_name":"4-aminoimidazole","common_names":["4-aminoimidazole","1H-Imidazol-4-amine","4919-03-3","5-Aminoimidazole","1H-imidazol-5-amine"]},"description":{"CID":484,"Title":"4-aminoimidazole"},"structure":{"atoms":{"1":{"aid":1,"element":"n","x":0.0234,"y":-1.0764,"z":-0.0002},"2":{"aid":2,"element":"n","x":-1.4413,"y":0.5931,"z":0.0004},"3":{"aid":3,"element":"n","x":2.1094,"y":0.0366,"z":0.0004},"4":{"aid":4,"element":"c","x":0.7645,"y":0.0717,"z":-0.0003},"5":{"aid":5,"element":"c","x":-0.1613,"y":1.0884,"z":-0.0004},"6":{"aid":6,"element":"c","x":-1.2947,"y":-0.7133,"z":0.0001},"7":{"aid":7,"element":"h","x":0.384,"y":-2.0211,"z":-0.0001},"8":{"aid":8,"element":"h","x":0.0259,"y":2.1526,"z":-0.0002},"9":{"aid":9,"element":"h","x":-2.0914,"y":-1.4434,"z":0.0005},"10":{"aid":10,"element":"h","x":2.6689,"y":0.8838,"z":0.0011},"11":{"aid":11,"element":"h","x":2.6318,"y":-0.8341,"z":0.001}},"bonds":{"1":{"bid":1,"vertices":[1,4],"order":"single"},"2":{"bid":2,"vertices":[1,6],"order":"single"},"3":{"bid":3,"vertices":[1,7],"order":"single"},"4":{"bid":4,"vertices":[2,5],"order":"single"},"5":{"bid":5,"vertices":[2,6],"order":"double"},"6":{"bid":6,"vertices":[3,4],"order":"single"},"7":{"bid":7,"vertices":[3,10],"order":"single"},"8":{"bid":8,"vertices":[3,11],"order":"single"},"9":{"bid":9,"vertices":[4,5],"order":"double"},"10":{"bid":10,"vertices":[5,8],"order":"single"},"11":{"bid":11,"vertices":[6,9],"order":"single"}}}}