{"cid":632,"name":"THDPA","properties":{"CID":632,"MolecularFormula":"C7H9NO4","MolecularWeight":171.15066,"IUPACName":"2,3,4,5-tetrahydropyridine-2,6-dicarboxylic acid","common_name":"THDPA","common_names":["THDPA","2,3,4,5-Tetrahydro-2,6-pyridinedicarboxylic acid","(S)-2,3,4,5-tetrahydrodipicolinic acid","2,3,4,5-tetrahydropyridine-2,6-dicarboxylic acid","2,3,4,5-Tetrahydro-2,6-dipicolinate"]},"description":{"CID":632,"Title":"2,3,4,5-tetrahydro-2,6-pyridinedicarboxylic acid"},"structure":{"atoms":{"1":{"aid":1,"element":"o","x":-3.5037,"y":-0.2712,"z":0.1853},"2":{"aid":2,"element":"o","x":-2.0268,"y":-1.9137,"z":-0.3775},"3":{"aid":3,"element":"o","x":2.9972,"y":-0.5241,"z":1.1365},"4":{"aid":4,"element":"o","x":2.7497,"y":-1.1738,"z":-1.0423},"5":{"aid":5,"element":"n","x":0.0538,"y":-0.5049,"z":0.362},"6":{"aid":6,"element":"c","x":-1.3062,"y":1.452,"z":-0.3774},"7":{"aid":7,"element":"c","x":-0.1275,"y":2.3506,"z":-0.047},"8":{"aid":8,"element":"c","x":-1.2237,"y":0.1956,"z":0.4771},"9":{"aid":9,"element":"c","x":1.1688,"y":1.6186,"z":-0.3406},"10":{"aid":10,"element":"c","x":1.1008,"y":0.1617,"z":0.0291},"11":{"aid":11,"element":"c","x":-2.2597,"y":-0.7913,"z":0.0459},"12":{"aid":12,"element":"c","x":2.3773,"y":-0.5997,"z":-0.051},"13":{"aid":13,"element":"h","x":-2.242,"y":1.9898,"z":-0.1853},"14":{"aid":14,"element":"h","x":-1.2991,"y":1.2007,"z":-1.4461},"15":{"aid":15,"element":"h","x":-0.1635,"y":2.6299,"z":1.0133},"16":{"aid":16,"element":"h","x":-0.1755,"y":3.2793,"z":-0.6259},"17":{"aid":17,"element":"h","x":-1.3958,"y":0.4249,"z":1.5358},"18":{"aid":18,"element":"h","x":2.0017,"y":2.094,"z":0.1879},"19":{"aid":19,"element":"h","x":1.3868,"y":1.6697,"z":-1.4142},"20":{"aid":20,"element":"h","x":-4.199,"y":-0.9039,"z":-0.0948},"21":{"aid":21,"element":"h","x":3.8491,"y":-1.0105,"z":1.142}},"bonds":{"1":{"bid":1,"vertices":[1,11],"order":"single"},"2":{"bid":2,"vertices":[1,20],"order":"single"},"3":{"bid":3,"vertices":[2,11],"order":"double"},"4":{"bid":4,"vertices":[3,12],"order":"single"},"5":{"bid":5,"vertices":[3,21],"order":"single"},"6":{"bid":6,"vertices":[4,12],"order":"double"},"7":{"bid":7,"vertices":[5,8],"order":"single"},"8":{"bid":8,"vertices":[5,10],"order":"double"},"9":{"bid":9,"vertices":[6,7],"order":"single"},"10":{"bid":10,"vertices":[6,8],"order":"single"},"11":{"bid":11,"vertices":[6,13],"order":"single"},"12":{"bid":12,"vertices":[6,14],"order":"single"},"13":{"bid":13,"vertices":[7,9],"order":"single"},"14":{"bid":14,"vertices":[7,15],"order":"single"},"15":{"bid":15,"vertices":[7,16],"order":"single"},"16":{"bid":16,"vertices":[8,11],"order":"single"},"17":{"bid":17,"vertices":[8,17],"order":"single"},"18":{"bid":18,"vertices":[9,10],"order":"single"},"19":{"bid":19,"vertices":[9,18],"order":"single"},"20":{"bid":20,"vertices":[9,19],"order":"single"},"21":{"bid":21,"vertices":[10,12],"order":"single"}}}}